darmo/__init__.py
darmo/factory.py
darmo/nasnet.py
darmo/network.py
darmo/nsga.py
darmo/operations.py
darmo/registry.py
darmo/resnet.py
darmo/tresnet.py
darmo/utils.py
darmo/version.py
darmo/config/eeea_c1.config
darmo/config/eeea_c1.subnet
darmo/config/eeea_c2.config
darmo/config/eeea_c2.subnet
darmo/config/ofa595.config
darmo/layers/tresnetv1/__init__.py
darmo/layers/tresnetv1/anti_aliasing.py
darmo/layers/tresnetv1/avg_pool.py
darmo/layers/tresnetv1/general_layers.py
darmo/layers/tresnetv1/inplace_abn.py
darmo/models/__init__.py
darmo/models/autoformer2.py
darmo/models/pnasnet5.py
darmo/models/pnasnet_ops.py
darmo/models/pyramid_vig.py
darmo/models/rest.py
darmo/models/gcn_lib/__init__.py
darmo/models/gcn_lib/pos_embed.py
darmo/models/gcn_lib/torch_edge.py
darmo/models/gcn_lib/torch_nn.py
darmo/models/gcn_lib/torch_vertex.py
darmo-0.1.15.dist-info/LICENSE
darmo-0.1.15.dist-info/METADATA
darmo-0.1.15.dist-info/WHEEL
darmo-0.1.15.dist-info/top_level.txt
darmo-0.1.15.dist-info/RECORD
