Metadata-Version: 2.1
Name: darmo
Version: 0.1.15
Summary: darts model pre-trained
Home-page: https://github.com/jitdee-ai/darmo
Author: Chakkrit Termritthikun
Author-email: chakkritt@nu.ac.th
License: UNKNOWN
Platform: UNKNOWN
Requires-Python: >=3.7
Requires-Dist: torch >=1.0
Requires-Dist: torchvision
Requires-Dist: ofa ==0.0.4.post2007200808
Requires-Dist: timm >=0.9.1
Requires-Dist: filelock
